fhirdatetime/__init__.py
fhirdatetime/_datetime.py
fhirdatetime-0.1.0b8.dist-info/LICENSE.txt
fhirdatetime-0.1.0b8.dist-info/WHEEL
fhirdatetime-0.1.0b8.dist-info/METADATA
fhirdatetime-0.1.0b8.dist-info/RECORD
