Metadata-Version: 2.1
Name: fhirdatetime
Version: 0.1.0b8
Summary: A datetime-compatible class for FHIR date/datetime values.
Home-page: https://github.com/mmabey/fhirdatetime
License: MIT
Author: Mike Mabey
Author-email: mmabey@ieee.org
Requires-Python: >=3.6.1,<4.0.0
Classifier: License :: OSI Approved :: MIT License
Classifier: Programming Language :: Python :: 3
Classifier: Programming Language :: Python :: 3.7
Classifier: Programming Language :: Python :: 3.8
Classifier: Programming Language :: Python :: 3.9
